textwrapre/LICENSE
textwrapre/README.MD
textwrapre/__init__.py
textwrapre/requirements.txt
textwrapre/thirdparty.json
textwrapre-0.10.dist-info/LICENSE.rst
textwrapre-0.10.dist-info/METADATA
textwrapre-0.10.dist-info/WHEEL
textwrapre-0.10.dist-info/top_level.txt
textwrapre-0.10.dist-info/RECORD
