Metadata-Version: 2.1
Name: textwrapre
Version: 0.10
Summary: Splits large texts into smaller ones that can't exceed a certain limit, but need to be split where a certain regular expression matches
Home-page: https://github.com/hansalemaos/textwrapre
Author: Johannes Fischer
Author-email: <aulasparticularesdealemaosp@gmail.com>
License: MIT
Keywords: textwrap,text,wrap,regex
Classifier: Development Status :: 4 - Beta
Classifier: Programming Language :: Python :: 3 :: Only
Classifier: Programming Language :: Python :: 3.10
Classifier: Topic :: Scientific/Engineering :: Visualization
Classifier: Topic :: Software Development :: Libraries :: Python Modules
Classifier: Topic :: Utilities
License-File: LICENSE.rst
Requires-Dist: regex
